owlwatch/__init__.py
owlwatch/client.py
owlwatch-0.0.5.dist-info/LICENSE
owlwatch-0.0.5.dist-info/METADATA
owlwatch-0.0.5.dist-info/WHEEL
owlwatch-0.0.5.dist-info/top_level.txt
owlwatch-0.0.5.dist-info/RECORD
