Metadata-Version: 2.1
Name: owlwatch
Version: 0.0.5
Summary: A python package to track ML algorithms and update user on error or success via email
Home-page: https://github.com/pypa/sampleproject
Author: Benjamin Hobson
Author-email: hobson.89@osu.edu
License: UNKNOWN
Project-URL: Bug Tracker, https://https://github.com/bjhobson12/OwlWatch/issues
Platform: UNKNOWN
Classifier: Programming Language :: Python :: 3
Classifier: License :: OSI Approved :: MIT License
Classifier: Operating System :: OS Independent
Requires-Python: >=3.6
License-File: LICENSE
